{
  "_class": "text",
  "attributedString": {
    "_class": "attributedString",
    "attributes": [
      {
        "_class": "stringAttribute",
        "attributes": {
          "MSAttributedStringColorAttribute": {
            "_class": "color",
            "alpha": 1,
            "blue": 0,
            "green": 0,
            "red": 0
          },
          "MSAttributedStringFontAttribute": {
            "_class": "fontDescriptor",
            "attributes": {
              "name": "Heebo-Regular",
              "size": 48
            }
          },
          "kerning": 0,
          "ligature": 0,
          "paragraphStyle": {
            "_class": "paragraphStyle",
            "alignment": 0,
            "allowsDefaultTighteningForTruncation": 0,
            "maximumLineHeight": 64,
            "minimumLineHeight": 64
          }
        },
        "length": 5,
        "location": 0
      }
    ],
    "string": "Jumbo"
  },
  "automaticallyDrawOnUnderlyingPath": false,
  "booleanOperation": 0,
  "clippingMaskMode": 0,
  "do_objectID": "9E14F01B-E72F-4169-A1E5-C9D6809A0B58",
  "dontSynchroniseWithSymbol": false,
  "exportOptions": {
    "_class": "exportOptions",
    "do_objectID": "D0844E37-2B95-4D16-AB36-A5B3AF52B356",
    "exportFormats": [
    ],
    "includedLayerIds": [
    ],
    "layerOptions": 0,
    "shouldTrim": false
  },
  "frame": {
    "_class": "rect",
    "constrainProportions": false,
    "do_objectID": "1893AFC4-A09F-438D-B459-962F05512EAB",
    "height": 64,
    "width": 150,
    "x": 616,
    "y": 163
  },
  "glyphBounds": "{{1, 11}, {147, 37}}",
  "hasClippingMask": false,
  "isFixedToViewport": false,
  "isFlippedHorizontal": false,
  "isFlippedVertical": false,
  "isLocked": false,
  "isVisible": true,
  "layerListExpandedType": 2,
  "lineSpacingBehaviour": 2,
  "name": "08 Jumbo/Black/Light - Left",
  "nameIsFixed": false,
  "resizingConstraint": 47,
  "resizingType": 0,
  "rotation": 0,
  "sharedStyleID": "553E6987-FD6D-4F37-B121-3A308AE76FCE",
  "shouldBreakMaskChain": false,
  "style": {
    "_class": "style",
    "contextSettings": {
      "_class": "graphicsContextSettings",
      "blendMode": 0,
      "do_objectID": "2B204070-703A-4C01-84D3-3BE2EC784389",
      "opacity": 0.5
    },
    "do_objectID": "06DC1577-3CA3-4644-985D-3CE95F9C4594",
    "endMarkerType": 0,
    "miterLimit": 10,
    "startMarkerType": 0,
    "textStyle": {
      "_class": "textStyle",
      "do_objectID": "01F01388-2518-4BF9-AC22-83A3B7B188C9",
      "encodedAttributes": {
        "MSAttributedStringColorAttribute": {
          "_class": "color",
          "alpha": 1,
          "blue": 0,
          "green": 0,
          "red": 0
        },
        "MSAttributedStringFontAttribute": {
          "_class": "fontDescriptor",
          "attributes": {
            "name": "Heebo-Regular",
            "size": 48
          }
        },
        "kerning": 0,
        "ligature": 0,
        "paragraphStyle": {
          "_class": "paragraphStyle",
          "alignment": 0,
          "allowsDefaultTighteningForTruncation": 0,
          "maximumLineHeight": 64,
          "minimumLineHeight": 64
        }
      },
      "verticalAlignment": 0
    },
    "windingRule": 1
  },
  "textBehaviour": 0,
  "userInfo": {
    "com.animaapp.stc-sketch-plugin": {
      "kModelPropertiesKey": {
        "isAutoWidth": 1
      }
    }
  }
}