{
  "_class": "shapePath",
  "booleanOperation": -1,
  "clippingMaskMode": 0,
  "do_objectID": "FE227F75-ACD6-413B-BC6B-B743E6FDA003",
  "edited": true,
  "exportOptions": {
    "_class": "exportOptions",
    "do_objectID": "E9742768-82D7-415E-9359-019120D18FCA",
    "exportFormats": [
    ],
    "includedLayerIds": [
    ],
    "layerOptions": 0,
    "shouldTrim": false
  },
  "frame": {
    "_class": "rect",
    "constrainProportions": false,
    "do_objectID": "E58EE147-9365-4E4F-B9A3-2F16AF4446ED",
    "height": 16,
    "width": 14.39089694057959,
    "x": 0,
    "y": 0
  },
  "hasClippingMask": false,
  "isClosed": true,
  "isFixedToViewport": false,
  "isFlippedHorizontal": false,
  "isFlippedVertical": false,
  "isLocked": false,
  "isVisible": true,
  "layerListExpandedType": 0,
  "name": "Path",
  "nameIsFixed": false,
  "pointRadiusBehaviour": 1,
  "points": [
    {
      "_class": "curvePoint",
      "cornerRadius": 0,
      "curveFrom": "{0.93966117077598066, 0.43690635768161284}",
      "curveMode": 4,
      "curveTo": "{0.96428679473604695, 0.4750141537133814}",
      "hasCurveFrom": true,
      "hasCurveTo": false,
      "point": "{0.96428679473604695, 0.4750141537133814}"
    },
    {
      "_class": "curvePoint",
      "cornerRadius": 0,
      "curveFrom": "{0.82935259416124729, 0.36641169679671159}",
      "curveMode": 3,
      "curveTo": "{0.90502193314173429, 0.40635617703565208}",
      "hasCurveFrom": true,
      "hasCurveTo": true,
      "point": "{0.86171532294660502, 0.38335680924139837}"
    },
    {
      "_class": "curvePoint",
      "cornerRadius": 0,
      "curveFrom": "{0.75797912569959225, 0.35103796972927198}",
      "curveMode": 4,
      "curveTo": "{0.79579488730903114, 0.35565689038360448}",
      "hasCurveFrom": false,
      "hasCurveTo": true,
      "point": "{0.75797912569959225, 0.35103796972927198}"
    },
    {
      "_class": "curvePoint",
      "cornerRadius": 0,
      "curveFrom": "{0.79579488730903114, 0.2155110828422809}",
      "curveMode": 4,
      "curveTo": "{0.75797912569959225, 0.22995286273793328}",
      "hasCurveFrom": true,
      "hasCurveTo": false,
      "point": "{0.75797912569959225, 0.22995286273793328}"
    },
    {
      "_class": "curvePoint",
      "cornerRadius": 0,
      "curveFrom": "{0.81926334896384889, 0.095425948363735871}",
      "curveMode": 3,
      "curveTo": "{0.81926334896384889, 0.18354597510338763}",
      "hasCurveFrom": true,
      "hasCurveTo": true,
      "point": "{0.81926334896384889, 0.14625448316369558}"
    },
    {
      "_class": "curvePoint",
      "cornerRadius": 0,
      "curveFrom": "{0.66096657086673793, 0.054236604384378821}",
      "curveMode": 2,
      "curveTo": "{0.77394494025109728, 0.054236604384378821}",
      "hasCurveFrom": true,
      "hasCurveTo": true,
      "point": "{0.7174784450158832, 0.054236604384378821}"
    },
    {
      "_class": "curvePoint",
      "cornerRadius": 0,
      "curveFrom": "{0.61485403116018789, 0.18354597510338763}",
      "curveMode": 3,
      "curveTo": "{0.61485403116018789, 0.095425948363735885}",
      "hasCurveFrom": true,
      "hasCurveTo": true,
      "point": "{0.61485403116018789, 0.14625448316369558}"
    },
    {
      "_class": "curvePoint",
      "cornerRadius": 0,
      "curveFrom": "{0.67478445015882638, 0.22995286273793328}",
      "curveMode": 4,
      "curveTo": "{0.6369686885493876, 0.2155110828422809}",
      "hasCurveFrom": false,
      "hasCurveTo": true,
      "point": "{0.67478445015882638, 0.22995286273793328}"
    },
    {
      "_class": "curvePoint",
      "cornerRadius": 0,
      "curveFrom": "{0.64453184087127535, 0.35502425471224525}",
      "curveMode": 4,
      "curveTo": "{0.67478445015882638, 0.35109239000207704}",
      "hasCurveFrom": true,
      "hasCurveTo": false,
      "point": "{0.67478445015882638, 0.35109239000207704}"
    },
    {
      "_class": "curvePoint",
      "cornerRadius": 0,
      "curveFrom": "{0.5259945545303284, 0.33656897969721705}",
      "curveMode": 4,
      "curveTo": "{0.61315988504008467, 0.3635070147357396}",
      "hasCurveFrom": true,
      "hasCurveTo": true,
      "point": "{0.58451066404477414, 0.37654067007256009}"
    },
    {
      "_class": "curvePoint",
      "cornerRadius": 0,
      "curveFrom": "{0.22453486613220397, 0.12021438262645716}",
      "curveMode": 4,
      "curveTo": "{0.33411738012403608, 0.20543652983923755}",
      "hasCurveFrom": true,
      "hasCurveTo": true,
      "point": "{0.22187263651489966, 0.1288467984001655}"
    },
    {
      "_class": "curvePoint",
      "cornerRadius": 0,
      "curveFrom": "{0.22658448041143567, 0.045631398747073025}",
      "curveMode": 3,
      "curveTo": "{0.22658448041143567, 0.11131666802282396}",
      "hasCurveFrom": true,
      "hasCurveTo": true,
      "point": "{0.22658448041143567, 0.10192917096394487}"
    },
    {
      "_class": "curvePoint",
      "cornerRadius": 0,
      "curveFrom": "{0.050665557404326246, 0}",
      "curveMode": 2,
      "curveTo": "{0.17589623355014386, 0}",
      "hasCurveFrom": true,
      "hasCurveTo": true,
      "point": "{0.11328089547723505, 0}"
    },
    {
      "_class": "curvePoint",
      "cornerRadius": 0,
      "curveFrom": "{0, 0.15822014064671613}",
      "curveMode": 2,
      "curveTo": "{0, 0.045631398747073039}",
      "hasCurveFrom": true,
      "hasCurveTo": true,
      "point": "{0, 0.1019291709639449}"
    },
    {
      "_class": "curvePoint",
      "cornerRadius": 0,
      "curveFrom": "{0.13469217970049946, 0.20386514446199039}",
      "curveMode": 3,
      "curveTo": "{0.050718499470579499, 0.20386514446199039}",
      "hasCurveFrom": true,
      "hasCurveTo": true,
      "point": "{0.1133338375434883, 0.20386514446199039}"
    },
    {
      "_class": "curvePoint",
      "cornerRadius": 0,
      "curveFrom": "{0.17149447889880523, 0.18900840998619917}",
      "curveMode": 4,
      "curveTo": "{0.15444713356527004, 0.1982462512948642}",
      "hasCurveFrom": false,
      "hasCurveTo": true,
      "point": "{0.17149447889880523, 0.18900840998619917}"
    },
    {
      "_class": "curvePoint",
      "cornerRadius": 0,
      "curveFrom": "{0.19518227197095775, 0.20517123100931267}",
      "curveMode": 1,
      "curveTo": "{0.19518227197095775, 0.20517123100931267}",
      "hasCurveFrom": false,
      "hasCurveTo": false,
      "point": "{0.19518227197095775, 0.20517123100931267}"
    },
    {
      "_class": "curvePoint",
      "cornerRadius": 0,
      "curveFrom": "{0.50346392376342519, 0.43031470213809558}",
      "curveMode": 4,
      "curveTo": "{0.52067009529571973, 0.41610420840186491}",
      "hasCurveFrom": true,
      "hasCurveTo": false,
      "point": "{0.52067009529571973, 0.41610420840186491}"
    },
    {
      "_class": "curvePoint",
      "cornerRadius": 0,
      "curveFrom": "{0.4486386325820606, 0.50158485191046942}",
      "curveMode": 3,
      "curveTo": "{0.48743760399334485, 0.44647752316120909}",
      "hasCurveFrom": true,
      "hasCurveTo": true,
      "point": "{0.4746180608077451, 0.46461307907350735}"
    },
    {
      "_class": "curvePoint",
      "cornerRadius": 0,
      "curveFrom": "{0.43276357585841829, 0.58663693577073395}",
      "curveMode": 4,
      "curveTo": "{0.43276357585841829, 0.54226400583227874}",
      "hasCurveFrom": false,
      "hasCurveTo": true,
      "point": "{0.43276357585841829, 0.58663693577073395}"
    },
    {
      "_class": "curvePoint",
      "cornerRadius": 0,
      "curveFrom": "{0.43276357585841829, 0.62704398832851771}",
      "curveMode": 4,
      "curveTo": "{0.43276357585841829, 0.59589518468170088}",
      "hasCurveFrom": true,
      "hasCurveTo": false,
      "point": "{0.43276357585841829, 0.59589518468170088}"
    },
    {
      "_class": "curvePoint",
      "cornerRadius": 0,
      "curveFrom": "{0.46042202389956172, 0.70819822014911726}",
      "curveMode": 2,
      "curveTo": "{0.4393435183784607, 0.65645134324557153}",
      "hasCurveFrom": true,
      "hasCurveTo": true,
      "point": "{0.45055211011949814, 0.68407643422825837}"
    },
    {
      "_class": "curvePoint",
      "cornerRadius": 0,
      "curveFrom": "{0.49272424746634447, 0.74995897699292779}",
      "curveMode": 4,
      "curveTo": "{0.47485251852972371, 0.7301295900895709}",
      "hasCurveFrom": false,
      "hasCurveTo": true,
      "point": "{0.49272424746634447, 0.74995897699292779}"
    },
    {
      "_class": "curvePoint",
      "cornerRadius": 0,
      "curveFrom": "{0.35272551401088936, 0.83665370263155237}",
      "curveMode": 4,
      "curveTo": "{0.38469974285282138, 0.84735766024584835}",
      "hasCurveFrom": true,
      "hasCurveTo": false,
      "point": "{0.38469974285282138, 0.84735766024584835}"
    },
    {
      "_class": "curvePoint",
      "cornerRadius": 0,
      "curveFrom": "{0.27621135740076291, 0.88025207119748317}",
      "curveMode": 3,
      "curveTo": "{0.31674616775104597, 0.84375044699489887}",
      "hasCurveFrom": true,
      "hasCurveTo": true,
      "point": "{0.29268643170473441, 0.86550682122634781}"
    },
    {
      "_class": "curvePoint",
      "cornerRadius": 0,
      "curveFrom": "{0.26707003479050051, 0.94225981348383492}",
      "curveMode": 2,
      "curveTo": "{0.26698376171441413, 0.9003151203816192}",
      "hasCurveFrom": true,
      "hasCurveTo": true,
      "point": "{0.26706247163817881, 0.92121957551056477}"
    },
    {
      "_class": "curvePoint",
      "cornerRadius": 0,
      "curveFrom": "{0.30911508306447549, 0.99174108670458205}",
      "curveMode": 2,
      "curveTo": "{0.27618363333837559, 0.96203478011438681}",
      "hasCurveFrom": true,
      "hasCurveTo": true,
      "point": "{0.29273181061866593, 0.97691192219248002}"
    },
    {
      "_class": "curvePoint",
      "cornerRadius": 0,
      "curveFrom": "{0.37790811218173004, 1.0000531874308667}",
      "curveMode": 4,
      "curveTo": "{0.3314158828173937, 1.0000553222178281}",
      "hasCurveFrom": true,
      "hasCurveTo": true,
      "point": "{0.35465890183028287, 0.99999972293004202}"
    },
    {
      "_class": "curvePoint",
      "cornerRadius": 0,
      "curveFrom": "{0.43307299474170335, 0.96216744587957759}",
      "curveMode": 2,
      "curveTo": "{0.40021508273324097, 0.99173969728459499}",
      "hasCurveFrom": true,
      "hasCurveTo": true,
      "point": "{0.4166086824988654, 0.9769119221924798}"
    },
    {
      "_class": "curvePoint",
      "cornerRadius": 0,
      "curveFrom": "{0.44224776887006484, 0.91307694219210211}",
      "curveMode": 3,
      "curveTo": "{0.44230376444104275, 0.94211668358665968}",
      "hasCurveFrom": true,
      "hasCurveTo": true,
      "point": "{0.44224776887006484, 0.92121957551056455}"
    },
    {
      "_class": "curvePoint",
      "cornerRadius": 0,
      "curveFrom": "{0.43821660868249851, 0.89758076951085108}",
      "curveMode": 4,
      "curveTo": "{0.44084858569051555, 0.90513158236255797}",
      "hasCurveFrom": false,
      "hasCurveTo": true,
      "point": "{0.43821660868249851, 0.89758076951085108}"
    },
    {
      "_class": "curvePoint",
      "cornerRadius": 0,
      "curveFrom": "{0.56517924671002828, 0.80665129618763631}",
      "curveMode": 4,
      "curveTo": "{0.54987142641052744, 0.79714135351494575}",
      "hasCurveFrom": true,
      "hasCurveTo": false,
      "point": "{0.54987142641052744, 0.79714135351494575}"
    },
    {
      "_class": "curvePoint",
      "cornerRadius": 0,
      "curveFrom": "{0.63454091665406098, 0.83519472927390925}",
      "curveMode": 3,
      "curveTo": "{0.58171229768567478, 0.81465787882408613}",
      "hasCurveFrom": true,
      "hasCurveTo": true,
      "point": "{0.59948570564211123, 0.82156245093623259}"
    },
    {
      "_class": "curvePoint",
      "cornerRadius": 0,
      "curveFrom": "{0.71558009378308862, 0.84350062341078691}",
      "curveMode": 4,
      "curveTo": "{0.67323400393283872, 0.84350062341078691}",
      "hasCurveFrom": false,
      "hasCurveTo": true,
      "point": "{0.71558009378308862, 0.84350062341078691}"
    },
    {
      "_class": "curvePoint",
      "cornerRadius": 0,
      "curveFrom": "{0.77015580093783087, 0.84350062341078691}",
      "curveMode": 4,
      "curveTo": "{0.72333988806534555, 0.84350062341078691}",
      "hasCurveFrom": true,
      "hasCurveTo": false,
      "point": "{0.72333988806534555, 0.84350062341078691}"
    },
    {
      "_class": "curvePoint",
      "cornerRadius": 0,
      "curveFrom": "{0.89957646346997411, 0.79199863773486423}",
      "curveMode": 2,
      "curveTo": "{0.8143170473453335, 0.83360973882846079}",
      "hasCurveFrom": true,
      "hasCurveTo": true,
      "point": "{0.8558311904401753, 0.8133790024131663}"
    },
    {
      "_class": "curvePoint",
      "cornerRadius": 0,
      "curveFrom": "{0.98568295265466621, 0.68800829893842641}",
      "curveMode": 2,
      "curveTo": "{0.93381485403115994, 0.76276134617032632}",
      "hasCurveFrom": true,
      "hasCurveTo": true,
      "point": "{0.95968083497201617, 0.72543584156013119}"
    },
    {
      "_class": "curvePoint",
      "cornerRadius": 0,
      "curveFrom": "{1, 0.60116034607559377}",
      "curveMode": 4,
      "curveTo": "{1, 0.64665569414065394}",
      "hasCurveFrom": false,
      "hasCurveTo": true,
      "point": "{1, 0.60116034607559377}"
    },
    {
      "_class": "curvePoint",
      "cornerRadius": 0,
      "curveFrom": "{1, 0.55413442783789024}",
      "curveMode": 4,
      "curveTo": "{1, 0.59888829968598101}",
      "hasCurveFrom": true,
      "hasCurveTo": false,
      "point": "{1, 0.59888829968598101}"
    },
    {
      "_class": "curvePoint",
      "cornerRadius": 0,
      "curveFrom": "{0.96428679473604606, 0.47501415371338113}",
      "curveMode": 4,
      "curveTo": "{0.98848131901376479, 0.51284304584702356}",
      "hasCurveFrom": false,
      "hasCurveTo": true,
      "point": "{0.96428679473604606, 0.47501415371338113}"
    }
  ],
  "resizingConstraint": 63,
  "resizingType": 0,
  "rotation": 0,
  "shouldBreakMaskChain": false,
  "style": {
    "_class": "style",
    "blur": {
      "_class": "blur",
      "center": "{0.5, 0.5}",
      "isEnabled": false,
      "motionAngle": 0,
      "radius": 48.828125,
      "saturation": 1,
      "type": 0
    },
    "endMarkerType": 0,
    "fills": [
      {
        "_class": "fill",
        "color": {
          "_class": "color",
          "alpha": 1,
          "blue": 0.1215686274509804,
          "green": 0.4627450980392157,
          "red": 0.9725490196078431
        },
        "fillType": 0,
        "isEnabled": true,
        "noiseIndex": 0,
        "noiseIntensity": 0,
        "patternFillType": 1,
        "patternTileScale": 1
      }
    ],
    "miterLimit": 10,
    "startMarkerType": 0,
    "windingRule": 0
  }
}