{
  "_class": "text",
  "attributedString": {
    "_class": "attributedString",
    "attributes": [
      {
        "_class": "stringAttribute",
        "attributes": {
          "MSAttributedStringColorAttribute": {
            "_class": "color",
            "alpha": 1,
            "blue": 0,
            "green": 0.8470588235294118,
            "red": 0.6509803921568628
          },
          "MSAttributedStringFontAttribute": {
            "_class": "fontDescriptor",
            "attributes": {
              "name": "Heebo-Regular",
              "size": 48
            }
          },
          "kerning": 0,
          "ligature": 0,
          "paragraphStyle": {
            "_class": "paragraphStyle",
            "alignment": 2,
            "allowsDefaultTighteningForTruncation": 0,
            "maximumLineHeight": 64,
            "minimumLineHeight": 64
          }
        },
        "length": 5,
        "location": 0
      }
    ],
    "string": "Jumbo"
  },
  "automaticallyDrawOnUnderlyingPath": false,
  "booleanOperation": 0,
  "clippingMaskMode": 0,
  "do_objectID": "01366245-6386-4ABC-A668-3BBC9F45905F",
  "dontSynchroniseWithSymbol": false,
  "exportOptions": {
    "_class": "exportOptions",
    "do_objectID": "40B3ED0D-7234-4EDB-94DC-10ED09FD13BB",
    "exportFormats": [
    ],
    "includedLayerIds": [
    ],
    "layerOptions": 0,
    "shouldTrim": false
  },
  "frame": {
    "_class": "rect",
    "constrainProportions": false,
    "do_objectID": "5BBE00AD-611E-4CD9-B945-A9753583D58C",
    "height": 64,
    "width": 150,
    "x": 616,
    "y": 1243
  },
  "glyphBounds": "{{1, 11}, {147, 37}}",
  "hasClippingMask": false,
  "isFixedToViewport": false,
  "isFlippedHorizontal": false,
  "isFlippedVertical": false,
  "isLocked": false,
  "isVisible": true,
  "layerListExpandedType": 2,
  "lineSpacingBehaviour": 2,
  "name": "08 Jumbo/Accent 2/Lighter - Center",
  "nameIsFixed": false,
  "resizingConstraint": 47,
  "resizingType": 0,
  "rotation": 0,
  "sharedStyleID": "9DD2DD98-1C1C-4B50-919A-FD7E1BF1E344",
  "shouldBreakMaskChain": false,
  "style": {
    "_class": "style",
    "contextSettings": {
      "_class": "graphicsContextSettings",
      "blendMode": 0,
      "do_objectID": "858F0047-6BEA-46C3-B3DF-143CE1955A53",
      "opacity": 0.25
    },
    "do_objectID": "21E5429E-7A8E-41EE-8E21-42A7624FBC5C",
    "endMarkerType": 0,
    "miterLimit": 10,
    "startMarkerType": 0,
    "textStyle": {
      "_class": "textStyle",
      "do_objectID": "FD47F18C-CAB9-4A20-A3F2-288AF3D33115",
      "encodedAttributes": {
        "MSAttributedStringColorAttribute": {
          "_class": "color",
          "alpha": 1,
          "blue": 0,
          "green": 0.8470588235294118,
          "red": 0.6509803921568628
        },
        "MSAttributedStringFontAttribute": {
          "_class": "fontDescriptor",
          "attributes": {
            "name": "Heebo-Regular",
            "size": 48
          }
        },
        "kerning": 0,
        "ligature": 0,
        "paragraphStyle": {
          "_class": "paragraphStyle",
          "alignment": 2,
          "allowsDefaultTighteningForTruncation": 0,
          "maximumLineHeight": 64,
          "minimumLineHeight": 64
        }
      },
      "verticalAlignment": 0
    },
    "windingRule": 1
  },
  "textBehaviour": 0,
  "userInfo": {
    "com.animaapp.stc-sketch-plugin": {
      "kModelPropertiesKey": {
        "isAutoWidth": 1
      }
    }
  }
}