{
  "_class": "text",
  "attributedString": {
    "_class": "attributedString",
    "attributes": [
      {
        "_class": "stringAttribute",
        "attributes": {
          "MSAttributedStringColorAttribute": {
            "_class": "color",
            "alpha": 1,
            "blue": 0,
            "green": 0.7019607843137254,
            "red": 1
          },
          "MSAttributedStringFontAttribute": {
            "_class": "fontDescriptor",
            "attributes": {
              "name": "Heebo-Regular",
              "size": 36
            }
          },
          "kerning": 0,
          "ligature": 0,
          "paragraphStyle": {
            "_class": "paragraphStyle",
            "alignment": 2,
            "allowsDefaultTighteningForTruncation": 0,
            "maximumLineHeight": 48,
            "minimumLineHeight": 48
          }
        },
        "length": 7,
        "location": 0
      }
    ],
    "string": "Display"
  },
  "automaticallyDrawOnUnderlyingPath": false,
  "booleanOperation": 0,
  "clippingMaskMode": 0,
  "do_objectID": "938C1BF8-6306-4763-ACF2-DCA5D3DDA097",
  "dontSynchroniseWithSymbol": false,
  "exportOptions": {
    "_class": "exportOptions",
    "do_objectID": "B1C8456C-B6FD-44D1-A2A7-0013253B7756",
    "exportFormats": [
    ],
    "includedLayerIds": [
    ],
    "layerOptions": 0,
    "shouldTrim": false
  },
  "frame": {
    "_class": "rect",
    "constrainProportions": false,
    "do_objectID": "25344E9E-C6DD-46AD-87A8-2104296A623C",
    "height": 48,
    "width": 117,
    "x": 476,
    "y": 643
  },
  "glyphBounds": "{{2, 8}, {115, 35}}",
  "hasClippingMask": false,
  "isFixedToViewport": false,
  "isFlippedHorizontal": false,
  "isFlippedVertical": false,
  "isLocked": false,
  "isVisible": true,
  "layerListExpandedType": 2,
  "lineSpacingBehaviour": 2,
  "name": "07 Display/Warning/Light - Center",
  "nameIsFixed": false,
  "resizingConstraint": 47,
  "resizingType": 0,
  "rotation": 0,
  "sharedStyleID": "84841FFF-8AAC-4381-AC18-2F64AD803CB7",
  "shouldBreakMaskChain": false,
  "style": {
    "_class": "style",
    "contextSettings": {
      "_class": "graphicsContextSettings",
      "blendMode": 0,
      "do_objectID": "2422F198-77FA-47E3-BD4E-70957865453A",
      "opacity": 0.5
    },
    "do_objectID": "7226EA6A-9AB5-4FAC-A61E-F2A67629FAF5",
    "endMarkerType": 0,
    "miterLimit": 10,
    "startMarkerType": 0,
    "textStyle": {
      "_class": "textStyle",
      "do_objectID": "7EE5C11B-DA58-4CEF-8E63-51436347D58C",
      "encodedAttributes": {
        "MSAttributedStringColorAttribute": {
          "_class": "color",
          "alpha": 1,
          "blue": 0,
          "green": 0.7019607843137254,
          "red": 1
        },
        "MSAttributedStringFontAttribute": {
          "_class": "fontDescriptor",
          "attributes": {
            "name": "Heebo-Regular",
            "size": 36
          }
        },
        "kerning": 0,
        "ligature": 0,
        "paragraphStyle": {
          "_class": "paragraphStyle",
          "alignment": 2,
          "allowsDefaultTighteningForTruncation": 0,
          "maximumLineHeight": 48,
          "minimumLineHeight": 48
        }
      },
      "verticalAlignment": 0
    },
    "windingRule": 1
  },
  "textBehaviour": 0,
  "userInfo": {
    "com.animaapp.stc-sketch-plugin": {
      "kModelPropertiesKey": {
        "isAutoWidth": 1
      }
    }
  }
}