{
  "_class": "group",
  "booleanOperation": -1,
  "clippingMaskMode": 0,
  "do_objectID": "A4928A5F-87C0-4646-A1C1-85D4726C28BF",
  "exportOptions": {
    "_class": "exportOptions",
    "exportFormats": [
    ],
    "includedLayerIds": [
    ],
    "layerOptions": 0,
    "shouldTrim": false
  },
  "frame": {
    "_class": "rect",
    "constrainProportions": false,
    "height": 49,
    "width": 6,
    "x": 79,
    "y": 63
  },
  "groupLayout": {
    "_class": "MSImmutableFreeformGroupLayout"
  },
  "hasClickThrough": false,
  "hasClippingMask": false,
  "isFixedToViewport": false,
  "isFlippedHorizontal": false,
  "isFlippedVertical": false,
  "isLocked": false,
  "isVisible": true,
  "layerListExpandedType": 0,
  "layers": [
    {
      "class": "rectangle",
      "id": "392FD4E2-3340-46CA-96E7-F471D319124C"
    },
    {
      "class": "rectangle",
      "id": "87AA8A6F-9AA0-44FF-AF43-FF149638D91F"
    },
    {
      "class": "rectangle",
      "id": "6CDB6B53-E07C-47CB-8D55-3DC865EC7B96"
    },
    {
      "class": "rectangle",
      "id": "A31ABD98-5F82-4348-B9DB-60D4300F5BE4"
    },
    {
      "class": "rectangle",
      "id": "88EBB415-C221-4F5B-89A9-DB4FABA1D666"
    },
    {
      "class": "rectangle",
      "id": "5F0AE0FB-6DAF-46E1-8D7F-2D21F2C83AED"
    },
    {
      "class": "rectangle",
      "id": "A9236C40-2366-4741-B14C-59C9C4376929"
    }
  ],
  "name": "Data Group",
  "nameIsFixed": false,
  "resizingConstraint": 63,
  "resizingType": 0,
  "rotation": 0,
  "shouldBreakMaskChain": false,
  "style": {
    "_class": "style",
    "endMarkerType": 0,
    "miterLimit": 10,
    "startMarkerType": 0,
    "windingRule": 1
  },
  "userInfo": {
    "com.animaapp.stc-sketch-plugin": {
      "kModelPropertiesKey": {
      }
    }
  }
}