{
  "_class": "group",
  "booleanOperation": -1,
  "clippingMaskMode": 0,
  "do_objectID": "EF111F14-264E-4EC4-A006-22C17DA1EF9C",
  "exportOptions": {
    "_class": "exportOptions",
    "do_objectID": "E09FE61F-A9FA-4D25-B03F-2CA7D8EA55EB",
    "exportFormats": [
    ],
    "includedLayerIds": [
    ],
    "layerOptions": 0,
    "shouldTrim": false
  },
  "frame": {
    "_class": "rect",
    "constrainProportions": false,
    "do_objectID": "BB55A8A9-3489-48DA-9B1C-521AFB0532B0",
    "height": 120,
    "width": 528,
    "x": 80,
    "y": 312
  },
  "groupLayout": {
    "_class": "MSImmutableFreeformGroupLayout"
  },
  "hasClickThrough": false,
  "hasClippingMask": false,
  "isFixedToViewport": false,
  "isFlippedHorizontal": false,
  "isFlippedVertical": false,
  "isLocked": false,
  "isVisible": true,
  "layerListExpandedType": 0,
  "layers": [
    {
      "class": "group",
      "id": "D78BFEDE-32AA-4D42-A30E-DC3274E159E6"
    },
    {
      "class": "group",
      "id": "CE17AD78-CF21-4196-B8BF-DDB7ED1842A6"
    }
  ],
  "name": "Twitter",
  "nameIsFixed": true,
  "resizingConstraint": 63,
  "resizingType": 0,
  "rotation": 0,
  "shouldBreakMaskChain": false,
  "style": {
    "_class": "style",
    "do_objectID": "8891DEDC-9AB3-48D2-9D3E-7899EDE29318",
    "endMarkerType": 0,
    "miterLimit": 10,
    "startMarkerType": 0,
    "windingRule": 1
  },
  "userInfo": {
    "com.animaapp.stc-sketch-plugin": {
      "kModelPropertiesKey": {
      }
    }
  }
}